kubeagentic/__init__.py
kubeagentic/cli.py
kubeagentic/exceptions.py
kubeagentic/api/__init__.py
kubeagentic/api/app.py
kubeagentic/api/models.py
kubeagentic/api/server.py
kubeagentic/api/streaming.py
kubeagentic/config/__init__.py
kubeagentic/config/parser.py
kubeagentic/config/schema.py
kubeagentic/config/validator.py
kubeagentic/core/__init__.py
kubeagentic/core/agent.py
kubeagentic/core/manager.py
kubeagentic/llm/__init__.py
kubeagentic/llm/factory.py
kubeagentic/llm/providers.py
kubeagentic/middleware/__init__.py
kubeagentic/middleware/rate_limit.py
kubeagentic/session/__init__.py
kubeagentic/session/manager.py
kubeagentic/session/storage.py
kubeagentic/tools/__init__.py
kubeagentic/tools/executor.py
kubeagentic/tools/registry.py
kubeagentic/utils/__init__.py
kubeagentic/utils/logging.py
kubeagentic-0.2.2.dist-info/licenses/LICENSE
kubeagentic-0.2.2.dist-info/METADATA
kubeagentic-0.2.2.dist-info/WHEEL
kubeagentic-0.2.2.dist-info/entry_points.txt
kubeagentic-0.2.2.dist-info/top_level.txt
kubeagentic-0.2.2.dist-info/RECORD
