Metadata-Version: 2.4
Name: kubeagentic
Version: 0.2.2
Summary: A Python library for building LangGraph agents from YAML configuration with OpenAI-compatible REST API
Author: KubeAgentic Contributors
License: MIT
Project-URL: Homepage, https://kubeagentic.com
Project-URL: Documentation, https://kubeagentic.com/guides
Project-URL: Repository, https://github.com/KubeAgentic-Community/kubeagenticpkg
Project-URL: Bug Tracker, https://github.com/KubeAgentic-Community/kubeagenticpkg/issues
Keywords: langgraph,langchain,agent,yaml,openai,api,llm
Classifier: Development Status :: 3 - Alpha
Classifier: Intended Audience :: Developers
Classifier: License :: OSI Approved :: MIT License
Classifier: Programming Language :: Python :: 3
Classifier: Programming Language :: Python :: 3.10
Classifier: Programming Language :: Python :: 3.11
Classifier: Programming Language :: Python :: 3.12
Requires-Python: >=3.10
License-File: LICENSE
Requires-Dist: langgraph>=0.2.0
Requires-Dist: langchain>=0.3.0
Requires-Dist: langchain-openai>=0.2.0
Requires-Dist: langchain-anthropic>=0.2.0
Requires-Dist: langchain-community>=0.3.0
Requires-Dist: pyyaml>=6.0
Requires-Dist: pydantic>=2.0
Requires-Dist: pydantic-settings>=2.0
Requires-Dist: jsonschema>=4.17
Requires-Dist: fastapi>=0.115.0
Requires-Dist: uvicorn[standard]>=0.30.0
Requires-Dist: python-multipart>=0.0.9
Requires-Dist: sse-starlette>=2.0.0
Requires-Dist: python-jose[cryptography]>=3.3.0
Requires-Dist: passlib[bcrypt]>=1.7.4
Requires-Dist: python-dotenv>=1.0.0
Requires-Dist: sqlalchemy>=2.0
Requires-Dist: alembic>=1.13
Requires-Dist: redis>=5.0
Requires-Dist: psycopg2-binary>=2.9
Requires-Dist: prometheus-client>=0.20.0
Requires-Dist: opentelemetry-api>=1.25
Requires-Dist: opentelemetry-sdk>=1.25
Requires-Dist: opentelemetry-instrumentation-fastapi>=0.46b0
Requires-Dist: tenacity>=8.2
Requires-Dist: aiofiles>=24.0
Requires-Dist: python-json-logger>=2.0
Requires-Dist: httpx>=0.27.0
Requires-Dist: tiktoken>=0.7.0
Requires-Dist: typer>=0.12.0
Requires-Dist: rich>=13.7.0
Provides-Extra: dev
Requires-Dist: pytest>=8.0; extra == "dev"
Requires-Dist: pytest-asyncio>=0.24; extra == "dev"
Requires-Dist: pytest-cov>=5.0; extra == "dev"
Requires-Dist: pytest-mock>=3.14; extra == "dev"
Requires-Dist: httpx>=0.27.0; extra == "dev"
Requires-Dist: black>=24.0; extra == "dev"
Requires-Dist: ruff>=0.6.0; extra == "dev"
Requires-Dist: mypy>=1.11; extra == "dev"
Requires-Dist: pre-commit>=3.8; extra == "dev"
Provides-Extra: test
Requires-Dist: pytest>=8.0; extra == "test"
Requires-Dist: pytest-asyncio>=0.24; extra == "test"
Requires-Dist: pytest-cov>=5.0; extra == "test"
Requires-Dist: pytest-mock>=3.14; extra == "test"
Requires-Dist: httpx>=0.27.0; extra == "test"
Requires-Dist: locust>=2.31; extra == "test"
Provides-Extra: docs
Requires-Dist: mkdocs>=1.6; extra == "docs"
Requires-Dist: mkdocs-material>=9.5; extra == "docs"
Requires-Dist: mkdocstrings[python]>=0.25; extra == "docs"
Provides-Extra: all
Requires-Dist: kubeagentic[dev,docs,test]; extra == "all"
Dynamic: license-file
